{"cameraMode":{"drawMode":0,"name":"Shaded","section":"Shading Mode"},"sceneLighting":true,"audioPlay":false,"sceneViewState":{"showFog":true,"showMaterialUpdate":false,"showSkybox":true,"showFlares":true,"showImageEffects":true,"showParticleSystems":true},"in2DMode":false,"pivot":{"x":4.854938507080078,"y":18.880491256713868,"z":-43.06330871582031},"rotation":{"x":-0.2350657433271408,"y":0.01370210014283657,"z":-0.0033133134711533787,"w":-0.9718812108039856},"size":0.541885256767273,"orthographic":false}